{
  "runtime": "Net80",
  "defaultVariables": "",
  "documentGenerator": {
    "fromDocument": {
      "json": "{\r\n  \"openapi\": \"3.0.1\",\r\n  \"info\": {\r\n    \"title\": \"Kaizen.Skills.Service\",\r\n    \"version\": \"latest\"\r\n  },\r\n  \"paths\": {\r\n    \"/api/skill-categories\": {\r\n      \"get\": {\r\n        \"tags\": [\r\n          \"SkillCategories\"\r\n        ],\r\n        \"operationId\": \"Find\",\r\n        \"parameters\": [\r\n          {\r\n            \"name\": \"Id\",\r\n            \"in\": \"query\",\r\n            \"style\": \"form\",\r\n            \"schema\": {\r\n              \"type\": \"integer\",\r\n              \"format\": \"int32\"\r\n            }\r\n          }\r\n        ],\r\n        \"responses\": {\r\n          \"200\": {\r\n            \"description\": \"OK\",\r\n            \"content\": {\r\n              \"application/json\": {\r\n                \"schema\": {\r\n                  \"$ref\": \"#/components/schemas/SkillCategoryItem\"\r\n                }\r\n              }\r\n            }\r\n          }\r\n        }\r\n      },\r\n      \"put\": {\r\n        \"tags\": [\r\n          \"SkillCategories\"\r\n        ],\r\n        \"operationId\": \"Create\",\r\n        \"requestBody\": {\r\n          \"content\": {\r\n            \"application/json\": {\r\n              \"schema\": {\r\n                \"$ref\": \"#/components/schemas/SkillCategoryCreateRequest\"\r\n              }\r\n            }\r\n          }\r\n        },\r\n        \"responses\": {\r\n          \"200\": {\r\n            \"description\": \"OK\",\r\n            \"content\": {\r\n              \"application/json\": {\r\n                \"schema\": {\r\n                  \"$ref\": \"#/components/schemas/SkillCategoryItem\"\r\n                }\r\n              }\r\n            }\r\n          }\r\n        }\r\n      },\r\n      \"post\": {\r\n        \"tags\": [\r\n          \"SkillCategories\"\r\n        ],\r\n        \"operationId\": \"Update\",\r\n        \"requestBody\": {\r\n          \"content\": {\r\n            \"application/json\": {\r\n              \"schema\": {\r\n                \"$ref\": \"#/components/schemas/SkillCategoryUpdateRequest\"\r\n              }\r\n            }\r\n          }\r\n        },\r\n        \"responses\": {\r\n          \"200\": {\r\n            \"description\": \"OK\",\r\n            \"content\": {\r\n              \"application/json\": {\r\n                \"schema\": {\r\n                  \"$ref\": \"#/components/schemas/SkillCategoryItem\"\r\n                }\r\n              }\r\n            }\r\n          }\r\n        }\r\n      }\r\n    },\r\n    \"/api/skill-categories/toggle-activity\": {\r\n      \"post\": {\r\n        \"tags\": [\r\n          \"SkillCategories\"\r\n        ],\r\n        \"operationId\": \"ChangeActive\",\r\n        \"requestBody\": {\r\n          \"content\": {\r\n            \"application/json\": {\r\n              \"schema\": {\r\n                \"$ref\": \"#/components/schemas/SkillCategoryChangeActiveRequest\"\r\n              }\r\n            }\r\n          }\r\n        },\r\n        \"responses\": {\r\n          \"200\": {\r\n            \"description\": \"OK\",\r\n            \"content\": {\r\n              \"application/json\": {\r\n                \"schema\": {\r\n                  \"$ref\": \"#/components/schemas/SkillCategoryItem\"\r\n                }\r\n              }\r\n            }\r\n          }\r\n        }\r\n      }\r\n    },\r\n    \"/api/skill/query\": {\r\n      \"post\": {\r\n        \"tags\": [\r\n          \"SkillCategories\"\r\n        ],\r\n        \"operationId\": \"Query\",\r\n        \"requestBody\": {\r\n          \"content\": {\r\n            \"application/json\": {\r\n              \"schema\": {\r\n                \"$ref\": \"#/components/schemas/SkillTreeFilter\"\r\n              }\r\n            }\r\n          }\r\n        },\r\n        \"responses\": {\r\n          \"200\": {\r\n            \"description\": \"OK\",\r\n            \"content\": {\r\n              \"application/json\": {\r\n                \"schema\": {\r\n                  \"type\": \"array\",\r\n                  \"items\": {\r\n                    \"$ref\": \"#/components/schemas/SkillTreeItem\"\r\n                  }\r\n                }\r\n              }\r\n            }\r\n          }\r\n        }\r\n      }\r\n    },\r\n    \"/api/skill-levels\": {\r\n      \"get\": {\r\n        \"tags\": [\r\n          \"SkillLevels\"\r\n        ],\r\n        \"operationId\": \"Find\",\r\n        \"parameters\": [\r\n          {\r\n            \"name\": \"Id\",\r\n            \"in\": \"query\",\r\n            \"style\": \"form\",\r\n            \"schema\": {\r\n              \"type\": \"integer\",\r\n              \"format\": \"int32\"\r\n            }\r\n          }\r\n        ],\r\n        \"responses\": {\r\n          \"200\": {\r\n            \"description\": \"OK\",\r\n            \"content\": {\r\n              \"application/json\": {\r\n                \"schema\": {\r\n                  \"$ref\": \"#/components/schemas/SkillLevelItem\"\r\n                }\r\n              }\r\n            }\r\n          }\r\n        }\r\n      },\r\n      \"put\": {\r\n        \"tags\": [\r\n          \"SkillLevels\"\r\n        ],\r\n        \"operationId\": \"Create\",\r\n        \"requestBody\": {\r\n          \"content\": {\r\n            \"application/json\": {\r\n              \"schema\": {\r\n                \"$ref\": \"#/components/schemas/SkillLevelCreateRequest\"\r\n              }\r\n            }\r\n          }\r\n        },\r\n        \"responses\": {\r\n          \"200\": {\r\n            \"description\": \"OK\",\r\n            \"content\": {\r\n              \"application/json\": {\r\n                \"schema\": {\r\n                  \"$ref\": \"#/components/schemas/SkillLevelItem\"\r\n                }\r\n              }\r\n            }\r\n          }\r\n        }\r\n      },\r\n      \"post\": {\r\n        \"tags\": [\r\n          \"SkillLevels\"\r\n        ],\r\n        \"operationId\": \"Update\",\r\n        \"requestBody\": {\r\n          \"content\": {\r\n            \"application/json\": {\r\n              \"schema\": {\r\n                \"$ref\": \"#/components/schemas/SkillLevelUpdateRequest\"\r\n              }\r\n            }\r\n          }\r\n        },\r\n        \"responses\": {\r\n          \"200\": {\r\n            \"description\": \"OK\",\r\n            \"content\": {\r\n              \"application/json\": {\r\n                \"schema\": {\r\n                  \"$ref\": \"#/components/schemas/SkillLevelItem\"\r\n                }\r\n              }\r\n            }\r\n          }\r\n        }\r\n      }\r\n    },\r\n    \"/api/skill-levels/toggle-activity\": {\r\n      \"post\": {\r\n        \"tags\": [\r\n          \"SkillLevels\"\r\n        ],\r\n        \"operationId\": \"ChangeActive\",\r\n        \"requestBody\": {\r\n          \"content\": {\r\n            \"application/json\": {\r\n              \"schema\": {\r\n                \"$ref\": \"#/components/schemas/SkillLevelChangeActiveRequest\"\r\n              }\r\n            }\r\n          }\r\n        },\r\n        \"responses\": {\r\n          \"200\": {\r\n            \"description\": \"OK\",\r\n            \"content\": {\r\n              \"application/json\": {\r\n                \"schema\": {\r\n                  \"$ref\": \"#/components/schemas/SkillLevelItem\"\r\n                }\r\n              }\r\n            }\r\n          }\r\n        }\r\n      }\r\n    },\r\n    \"/api/skills\": {\r\n      \"get\": {\r\n        \"tags\": [\r\n          \"Skills\"\r\n        ],\r\n        \"operationId\": \"Find\",\r\n        \"parameters\": [\r\n          {\r\n            \"name\": \"Id\",\r\n            \"in\": \"query\",\r\n            \"style\": \"form\",\r\n            \"schema\": {\r\n              \"type\": \"integer\",\r\n              \"format\": \"int32\"\r\n            }\r\n          }\r\n        ],\r\n        \"responses\": {\r\n          \"200\": {\r\n            \"description\": \"OK\",\r\n            \"content\": {\r\n              \"application/json\": {\r\n                \"schema\": {\r\n                  \"$ref\": \"#/components/schemas/SkillItem\"\r\n                }\r\n              }\r\n            }\r\n          }\r\n        }\r\n      },\r\n      \"post\": {\r\n        \"tags\": [\r\n          \"Skills\"\r\n        ],\r\n        \"operationId\": \"Update\",\r\n        \"requestBody\": {\r\n          \"content\": {\r\n            \"application/json\": {\r\n              \"schema\": {\r\n                \"$ref\": \"#/components/schemas/SkillUpdateRequest\"\r\n              }\r\n            }\r\n          }\r\n        },\r\n        \"responses\": {\r\n          \"200\": {\r\n            \"description\": \"OK\",\r\n            \"content\": {\r\n              \"application/json\": {\r\n                \"schema\": {\r\n                  \"$ref\": \"#/components/schemas/SkillItem\"\r\n                }\r\n              }\r\n            }\r\n          }\r\n        }\r\n      },\r\n      \"put\": {\r\n        \"tags\": [\r\n          \"Skills\"\r\n        ],\r\n        \"operationId\": \"Create\",\r\n        \"requestBody\": {\r\n          \"content\": {\r\n            \"application/json\": {\r\n              \"schema\": {\r\n                \"$ref\": \"#/components/schemas/SkillCreateRequest\"\r\n              }\r\n            }\r\n          }\r\n        },\r\n        \"responses\": {\r\n          \"200\": {\r\n            \"description\": \"OK\",\r\n            \"content\": {\r\n              \"application/json\": {\r\n                \"schema\": {\r\n                  \"$ref\": \"#/components/schemas/SkillItem\"\r\n                }\r\n              }\r\n            }\r\n          }\r\n        }\r\n      }\r\n    },\r\n    \"/api/skills/toggle-activity\": {\r\n      \"post\": {\r\n        \"tags\": [\r\n          \"Skills\"\r\n        ],\r\n        \"operationId\": \"ChangeActive\",\r\n        \"requestBody\": {\r\n          \"content\": {\r\n            \"application/json\": {\r\n              \"schema\": {\r\n                \"$ref\": \"#/components/schemas/SkillChangeActiveRequest\"\r\n              }\r\n            }\r\n          }\r\n        },\r\n        \"responses\": {\r\n          \"200\": {\r\n            \"description\": \"OK\",\r\n            \"content\": {\r\n              \"application/json\": {\r\n                \"schema\": {\r\n                  \"$ref\": \"#/components/schemas/SkillItem\"\r\n                }\r\n              }\r\n            }\r\n          }\r\n        }\r\n      }\r\n    }\r\n  },\r\n  \"components\": {\r\n    \"schemas\": {\r\n      \"IncludeActiveOption\": {\r\n        \"enum\": [\r\n          \"None\",\r\n          \"IncludeOnlyActive\",\r\n          \"IncludeOnlyInactive\",\r\n          \"IncludeAll\"\r\n        ],\r\n        \"type\": \"string\"\r\n      },\r\n      \"SkillAggregationLevel\": {\r\n        \"enum\": [\r\n          \"None\",\r\n          \"SkillCategory\",\r\n          \"Skill\",\r\n          \"SkillLevel\"\r\n        ],\r\n        \"type\": \"string\"\r\n      },\r\n      \"SkillCategoryChangeActiveRequest\": {\r\n        \"type\": \"object\",\r\n        \"properties\": {\r\n          \"toUpdate\": {\r\n            \"$ref\": \"#/components/schemas/SkillCategorySelector\"\r\n          },\r\n          \"isActive\": {\r\n            \"type\": \"boolean\",\r\n            \"nullable\": true\r\n          }\r\n        },\r\n        \"additionalProperties\": false\r\n      },\r\n      \"SkillCategoryCreateRequest\": {\r\n        \"type\": \"object\",\r\n        \"properties\": {\r\n          \"name\": {\r\n            \"type\": \"string\",\r\n            \"nullable\": true\r\n          },\r\n          \"shortDescription\": {\r\n            \"type\": \"string\",\r\n            \"nullable\": true\r\n          }\r\n        },\r\n        \"additionalProperties\": false\r\n      },\r\n      \"SkillCategoryItem\": {\r\n        \"type\": \"object\",\r\n        \"properties\": {\r\n          \"id\": {\r\n            \"type\": \"integer\",\r\n            \"format\": \"int32\"\r\n          },\r\n          \"isActive\": {\r\n            \"type\": \"boolean\"\r\n          },\r\n          \"name\": {\r\n            \"type\": \"string\",\r\n            \"nullable\": true\r\n          },\r\n          \"shortDescription\": {\r\n            \"type\": \"string\",\r\n            \"nullable\": true\r\n          },\r\n          \"items\": {\r\n            \"type\": \"array\",\r\n            \"items\": {\r\n              \"$ref\": \"#/components/schemas/SkillItem\"\r\n            },\r\n            \"nullable\": true\r\n          },\r\n          \"nodeType\": {\r\n            \"$ref\": \"#/components/schemas/SkillAggregationLevel\"\r\n          }\r\n        },\r\n        \"additionalProperties\": false\r\n      },\r\n      \"SkillCategorySelector\": {\r\n        \"type\": \"object\",\r\n        \"properties\": {\r\n          \"id\": {\r\n            \"type\": \"integer\",\r\n            \"format\": \"int32\",\r\n            \"nullable\": true\r\n          }\r\n        },\r\n        \"additionalProperties\": false\r\n      },\r\n      \"SkillCategoryUpdateRequest\": {\r\n        \"type\": \"object\",\r\n        \"properties\": {\r\n          \"name\": {\r\n            \"type\": \"string\",\r\n            \"nullable\": true\r\n          },\r\n          \"shortDescription\": {\r\n            \"type\": \"string\",\r\n            \"nullable\": true\r\n          },\r\n          \"isActive\": {\r\n            \"type\": \"boolean\",\r\n            \"nullable\": true\r\n          },\r\n          \"toUpdate\": {\r\n            \"$ref\": \"#/components/schemas/SkillCategorySelector\"\r\n          }\r\n        },\r\n        \"additionalProperties\": false\r\n      },\r\n      \"SkillChangeActiveRequest\": {\r\n        \"type\": \"object\",\r\n        \"properties\": {\r\n          \"toUpdate\": {\r\n            \"$ref\": \"#/components/schemas/SkillSelector\"\r\n          },\r\n          \"isActive\": {\r\n            \"type\": \"boolean\",\r\n            \"nullable\": true\r\n          }\r\n        },\r\n        \"additionalProperties\": false\r\n      },\r\n      \"SkillCreateRequest\": {\r\n        \"type\": \"object\",\r\n        \"properties\": {\r\n          \"name\": {\r\n            \"type\": \"string\",\r\n            \"nullable\": true\r\n          },\r\n          \"shortDescription\": {\r\n            \"type\": \"string\",\r\n            \"nullable\": true\r\n          },\r\n          \"parent\": {\r\n            \"$ref\": \"#/components/schemas/SkillCategorySelector\"\r\n          }\r\n        },\r\n        \"additionalProperties\": false\r\n      },\r\n      \"SkillItem\": {\r\n        \"type\": \"object\",\r\n        \"properties\": {\r\n          \"id\": {\r\n            \"type\": \"integer\",\r\n            \"format\": \"int32\"\r\n          },\r\n          \"isActive\": {\r\n            \"type\": \"boolean\"\r\n          },\r\n          \"name\": {\r\n            \"type\": \"string\",\r\n            \"nullable\": true\r\n          },\r\n          \"shortDescription\": {\r\n            \"type\": \"string\",\r\n            \"nullable\": true\r\n          },\r\n          \"items\": {\r\n            \"type\": \"array\",\r\n            \"items\": {\r\n              \"$ref\": \"#/components/schemas/SkillLevelItem\"\r\n            },\r\n            \"nullable\": true\r\n          },\r\n          \"nodeType\": {\r\n            \"$ref\": \"#/components/schemas/SkillAggregationLevel\"\r\n          }\r\n        },\r\n        \"additionalProperties\": false\r\n      },\r\n      \"SkillLevelChangeActiveRequest\": {\r\n        \"type\": \"object\",\r\n        \"properties\": {\r\n          \"toUpdate\": {\r\n            \"$ref\": \"#/components/schemas/SkillLevelSelector\"\r\n          },\r\n          \"isActive\": {\r\n            \"type\": \"boolean\",\r\n            \"nullable\": true\r\n          }\r\n        },\r\n        \"additionalProperties\": false\r\n      },\r\n      \"SkillLevelCreateRequest\": {\r\n        \"type\": \"object\",\r\n        \"properties\": {\r\n          \"name\": {\r\n            \"type\": \"string\",\r\n            \"nullable\": true\r\n          },\r\n          \"shortDescription\": {\r\n            \"type\": \"string\",\r\n            \"nullable\": true\r\n          },\r\n          \"description\": {\r\n            \"type\": \"string\",\r\n            \"nullable\": true\r\n          },\r\n          \"weight\": {\r\n            \"type\": \"integer\",\r\n            \"format\": \"int32\",\r\n            \"nullable\": true\r\n          },\r\n          \"parent\": {\r\n            \"$ref\": \"#/components/schemas/SkillSelector\"\r\n          }\r\n        },\r\n        \"additionalProperties\": false\r\n      },\r\n      \"SkillLevelItem\": {\r\n        \"type\": \"object\",\r\n        \"properties\": {\r\n          \"id\": {\r\n            \"type\": \"integer\",\r\n            \"format\": \"int32\"\r\n          },\r\n          \"isActive\": {\r\n            \"type\": \"boolean\"\r\n          },\r\n          \"name\": {\r\n            \"type\": \"string\",\r\n            \"nullable\": true\r\n          },\r\n          \"shortDescription\": {\r\n            \"type\": \"string\",\r\n            \"nullable\": true\r\n          },\r\n          \"weight\": {\r\n            \"type\": \"integer\",\r\n            \"format\": \"int32\"\r\n          },\r\n          \"description\": {\r\n            \"type\": \"string\",\r\n            \"nullable\": true\r\n          },\r\n          \"prerequisites\": {\r\n            \"type\": \"array\",\r\n            \"items\": {\r\n              \"$ref\": \"#/components/schemas/SkillLevelPrerequisiteItem\"\r\n            },\r\n            \"nullable\": true\r\n          },\r\n          \"nodeType\": {\r\n            \"$ref\": \"#/components/schemas/SkillAggregationLevel\"\r\n          }\r\n        },\r\n        \"additionalProperties\": false\r\n      },\r\n      \"SkillLevelPrerequisiteItem\": {\r\n        \"type\": \"object\",\r\n        \"properties\": {\r\n          \"prerequisiteId\": {\r\n            \"type\": \"integer\",\r\n            \"format\": \"int32\"\r\n          },\r\n          \"requiredSkillId\": {\r\n            \"type\": \"integer\",\r\n            \"format\": \"int32\"\r\n          }\r\n        },\r\n        \"additionalProperties\": false\r\n      },\r\n      \"SkillLevelSelector\": {\r\n        \"type\": \"object\",\r\n        \"properties\": {\r\n          \"id\": {\r\n            \"type\": \"integer\",\r\n            \"format\": \"int32\",\r\n            \"nullable\": true\r\n          }\r\n        },\r\n        \"additionalProperties\": false\r\n      },\r\n      \"SkillLevelUpdateRequest\": {\r\n        \"type\": \"object\",\r\n        \"properties\": {\r\n          \"toUpdate\": {\r\n            \"$ref\": \"#/components/schemas/SkillLevelSelector\"\r\n          },\r\n          \"name\": {\r\n            \"type\": \"string\",\r\n            \"nullable\": true\r\n          },\r\n          \"shortDescription\": {\r\n            \"type\": \"string\",\r\n            \"nullable\": true\r\n          },\r\n          \"isActive\": {\r\n            \"type\": \"boolean\",\r\n            \"nullable\": true\r\n          },\r\n          \"description\": {\r\n            \"type\": \"string\",\r\n            \"nullable\": true\r\n          },\r\n          \"weight\": {\r\n            \"type\": \"integer\",\r\n            \"format\": \"int32\",\r\n            \"nullable\": true\r\n          }\r\n        },\r\n        \"additionalProperties\": false\r\n      },\r\n      \"SkillSelector\": {\r\n        \"type\": \"object\",\r\n        \"properties\": {\r\n          \"id\": {\r\n            \"type\": \"integer\",\r\n            \"format\": \"int32\",\r\n            \"nullable\": true\r\n          }\r\n        },\r\n        \"additionalProperties\": false\r\n      },\r\n      \"SkillTreeFilter\": {\r\n        \"type\": \"object\",\r\n        \"properties\": {\r\n          \"includeActive\": {\r\n            \"$ref\": \"#/components/schemas/IncludeActiveOption\"\r\n          }\r\n        },\r\n        \"additionalProperties\": false\r\n      },\r\n      \"SkillTreeItem\": {\r\n        \"type\": \"object\",\r\n        \"properties\": {\r\n          \"id\": {\r\n            \"type\": \"integer\",\r\n            \"format\": \"int32\"\r\n          },\r\n          \"name\": {\r\n            \"type\": \"string\",\r\n            \"nullable\": true\r\n          },\r\n          \"isActive\": {\r\n            \"type\": \"boolean\"\r\n          },\r\n          \"nodeType\": {\r\n            \"$ref\": \"#/components/schemas/SkillAggregationLevel\"\r\n          },\r\n          \"items\": {\r\n            \"type\": \"array\",\r\n            \"items\": {\r\n              \"$ref\": \"#/components/schemas/SkillTreeItem\"\r\n            },\r\n            \"nullable\": true\r\n          }\r\n        },\r\n        \"additionalProperties\": false\r\n      },\r\n      \"SkillUpdateRequest\": {\r\n        \"type\": \"object\",\r\n        \"properties\": {\r\n          \"toUpdate\": {\r\n            \"$ref\": \"#/components/schemas/SkillSelector\"\r\n          },\r\n          \"name\": {\r\n            \"type\": \"string\",\r\n            \"nullable\": true\r\n          },\r\n          \"shortDescription\": {\r\n            \"type\": \"string\",\r\n            \"nullable\": true\r\n          },\r\n          \"isActive\": {\r\n            \"type\": \"boolean\",\r\n            \"nullable\": true\r\n          }\r\n        },\r\n        \"additionalProperties\": false\r\n      }\r\n    },\r\n    \"securitySchemes\": {\r\n      \"Bearer\": {\r\n        \"type\": \"apiKey\",\r\n        \"description\": \"JWT Authorization header using the Bearer scheme. \\\\r\\\\n\\\\r\\\\n \\r\\n                      Enter 'Bearer' [space] and then your token in the text input below.\\r\\n                      \\\\r\\\\n\\\\r\\\\nExample: 'Bearer 12345abcdef'\",\r\n        \"name\": \"Authorization\",\r\n        \"in\": \"header\"\r\n      }\r\n    }\r\n  },\r\n  \"security\": [\r\n    {\r\n      \"Bearer\": []\r\n    }\r\n  ]\r\n}",
      "url": "http://localhost:5000/swagger/latest/swagger.json",
      "output": null,
      "newLineBehavior": "Auto"
    }
  },
  "codeGenerators": {
    "openApiToTypeScriptClient": {
      "className": "{controller}Client",
      "moduleName": "",
      "namespace": "",
      "typeScriptVersion": 4.3,
      "template": "Angular",
      "promiseType": "Promise",
      "httpClass": "HttpClient",
      "withCredentials": false,
      "useSingletonProvider": true,
      "injectionTokenType": "InjectionToken",
      "rxJsVersion": 6.0,
      "dateTimeType": "Date",
      "nullValue": "Undefined",
      "generateClientClasses": true,
      "generateClientInterfaces": false,
      "generateOptionalParameters": false,
      "exportTypes": true,
      "wrapDtoExceptions": false,
      "exceptionClass": "ApiException",
      "clientBaseClass": null,
      "wrapResponses": false,
      "wrapResponseMethods": [],
      "generateResponseClasses": true,
      "responseClass": "SwaggerResponse",
      "protectedMethods": [],
      "configurationClass": null,
      "useTransformOptionsMethod": false,
      "useTransformResultMethod": false,
      "generateDtoTypes": true,
      "operationGenerationMode": "MultipleClientsFromFirstTagAndOperationId",
      "markOptionalProperties": true,
      "generateCloneMethod": false,
      "typeStyle": "Interface",
      "enumStyle": "Enum",
      "useLeafType": false,
      "classTypes": [],
      "extendedClasses": [],
      "extensionCode": null,
      "generateDefaultValues": true,
      "excludedTypeNames": [],
      "excludedParameterNames": [],
      "handleReferences": false,
      "generateTypeCheckFunctions": false,
      "generateConstructorInterface": true,
      "convertConstructorInterfaceData": false,
      "importRequiredTypes": true,
      "useGetBaseUrlMethod": false,
      "baseUrlTokenName": "API_BASE_URL",
      "queryNullValue": "",
      "useAbortSignal": false,
      "inlineNamedDictionaries": false,
      "inlineNamedAny": false,
      "includeHttpContext": false,
      "templateDirectory": null,
      "serviceHost": null,
      "serviceSchemes": null,
      "output": null,
      "newLineBehavior": "Auto"
    }
  }
}